Challenge_lists/Challenge#19/Code/lif_neuron.sv

module lif_neuron #(
    parameter WIDTH      = 16,          // Q1.15 width
    parameter LAMBDA     = 16'd32768,   // 0.5  (Q1.15)
    parameter THRESHOLD  = 16'd49152    // 1.5  (Q1.15)
)(
    input  logic                  clk,
    input  logic                  rst,
    input  logic                  in_bit,          // binary input
    output logic                  spike,           // cycle pulse
    output logic [WIDTH-1:0]      potential        // membrane potential
);

    logic [WIDTH-1:0]  input_fixed;                // 1.0 or 0.0
    logic [31:0]       mult_result;                // Q2.30 product
    logic [WIDTH:0]    mult_scaled;                // one bit wider (Q1.15)
    logic [WIDTH:0]    next_potential;             // one bit wider
    logic              spike_next;                 // comb comparator

    always_comb begin
        input_fixed   = {in_bit, 15'b0};
        mult_result   = potential * LAMBDA;
        mult_scaled   = mult_result[31:16];
        next_potential= mult_scaled + input_fixed;
        spike_next    = (next_potential >= THRESHOLD);
    end

    always_ff @(posedge clk or posedge rst) begin
        if (rst) begin
            potential <= '0;
            spike     <= 1'b0;
        end else begin
            spike <= spike_next;
            if (spike_next)
                potential <= '0;
            else
                potential <= next_potential[WIDTH-1:0]; // keep lower 16 bits
        end
    end
endmodule

Challenge_lists/Challenge#19/Code/wave.vcd
$version Generated by VerilatedVcd $end
$timescale 1ps $end
 $scope module TOP $end
  $var wire 1 ( clk $end
  $var wire 1 ) rst $end
  $var wire 1 * in_bit $end
  $var wire 1 + spike $end
  $var wire 16 , potential [15:0] $end
  $scope module lif_neuron $end
   $var wire 32 - WIDTH [31:0] $end
   $var wire 16 . LAMBDA [15:0] $end
   $var wire 16 / THRESHOLD [15:0] $end
   $var wire 1 ( clk $end
   $var wire 1 ) rst $end
   $var wire 1 * in_bit $end
   $var wire 1 + spike $end
   $var wire 16 , potential [15:0] $end
   $var wire 16 # input_fixed [15:0] $end
   $var wire 32 $ mult_result [31:0] $end
   $var wire 17 % mult_scaled [16:0] $end
   $var wire 17 & next_potential [16:0] $end
   $var wire 1 ' spike_next $end
  $upscope $end
 $upscope $end
$enddefinitions $end


#0
b0000000000000000 #
b00000000000000000000000000000000 $
b00000000000000000 %
b00000000000000000 &
0'
0(
1)
0*
0+
b0000000000000000 ,
b00000000000000000000000000010000 -
b1000000000000000 .
b1100000000000000 /
#5
1(
#10
0(
0)
#15
1(
#20
0(
#25
1(
#30
0(
#35
1(
#40
0(
#45
1(
#50
0(
#55
1(
#60
0(
#65
1(
#70
0(
#75
1(
#80
0(
#85
1(
#90
0(
#95
1(
#100
0(
#105
1(
#110
0(
#115
1(
#120
0(
#125
1(
#130
0(
#135
1(
#140
0(
#145
1(
#150
0(
#155
1(
#160
0(
#165
1(
#170
0(
#175
1(
#180
0(
#185
1(
#190
0(
#195
1(
#200
0(
#205
1(
#210
0(
#215
1(
#220
0(
#225
1(
#230
0(
#235
1(
#240
0(
#245
1(
#250
0(
#255
1(
#260
0(
#265
1(
#270
0(
#275
1(
#280
0(
#285
1(
#290
0(
#295
1(
#300
0(
#305
1(
#310
0(
#315
1(
#320
0(
#325
1(
#330
0(
#335
1(
#340
0(
#345
1(
#350
0(
#355
1(
#360
0(
#365
1(
#370
0(
#375
1(
#380
0(
#385
1(
#390
0(
#395
1(
#400
0(
#405
1(
#410
0(
#415
1(
#420
0(
#425
1(
#430
0(
#435
1(
#440
0(
#445
1(
#450
0(
#455
1(
#460
0(
#465
1(
#470
0(
#475
1(
#480
0(
#485
1(
#490
0(
#495
1(
#500
0(
#505
1(
#510
b1000000000000000 #
b01000000000000000 &
0(
1*
#515
b01000000000000000000000000000000 $
b00100000000000000 %
b01100000000000000 &
1'
1(
b1000000000000000 ,
#520
0(
#525
b00000000000000000000000000000000 $
b00000000000000000 %
b01000000000000000 &
0'
1(
1+
b0000000000000000 ,
#530
b0000000000000000 #
b00000000000000000 &
0(
0*
#535
1(
0+
#540
0(
#545
1(
#550
0(
#555
1(
#560
0(
#565
1(
#570
0(
#575
1(
#580
0(
#585
1(
#590
0(
#595
1(
#600
0(
#605
1(
#610
0(
#615
1(
#620
0(
#625
1(
#630
0(
#635
1(
#640
0(
#645
1(
#650
0(
#655
1(
#660
0(
#665
1(
#670
0(
#675
1(
#680
0(
#685
1(
#690
0(
#695
1(
#700
0(
#705
1(
#710
0(
#715
1(
#720
0(
#725
1(
#730
0(
#735
1(
#740
0(
#745
1(
#750
0(
#755
1(
#760
0(
#765
1(
#770
0(
#775
1(
#780
0(
#785
1(
#790
0(
#795
1(
#800
0(
#805
1(
#810
0(
#815
1(
#820
0(
#825
1(
#830
0(
#835
1(
#840
0(
#845
1(
#850
0(
#855
1(
#860
0(
#865
1(
#870
0(
#875
1(
#880
0(
#885
1(
#890
0(
#895
1(
#900
0(
#905
1(
#910
0(
#915
1(
#920
0(
#925
1(
#930
0(
1)
#935
1(
#940
b1000000000000000 #
b01000000000000000 &
0(
0)
1*
#945
b01000000000000000000000000000000 $
b00100000000000000 %
b01100000000000000 &
1'
1(
b1000000000000000 ,
#950
0(
#955
b00000000000000000000000000000000 $
b00000000000000000 %
b01000000000000000 &
0'
1(
1+
b0000000000000000 ,
